jigsawstack/__init__.py
jigsawstack/_config.py
jigsawstack/_types.py
jigsawstack/async_request.py
jigsawstack/audio.py
jigsawstack/classification.py
jigsawstack/embedding.py
jigsawstack/embedding_v2.py
jigsawstack/exceptions.py
jigsawstack/helpers.py
jigsawstack/image_generation.py
jigsawstack/prediction.py
jigsawstack/prompt_engine.py
jigsawstack/request.py
jigsawstack/search.py
jigsawstack/sentiment.py
jigsawstack/sql.py
jigsawstack/store.py
jigsawstack/summary.py
jigsawstack/translate.py
jigsawstack/validate.py
jigsawstack/version.py
jigsawstack/vision.py
jigsawstack/web.py
jigsawstack-0.3.7.dist-info/METADATA
jigsawstack-0.3.7.dist-info/WHEEL
jigsawstack-0.3.7.dist-info/top_level.txt
jigsawstack-0.3.7.dist-info/RECORD
