Metadata-Version: 2.4
Name: jigsawstack
Version: 0.3.7
Summary: JigsawStack - The AI SDK for Python
Home-page: https://github.com/jigsawstack/jigsawstack-python
Author: JigsawStack
Author-email: hello@jigsawstack.com
Keywords: AI,AI Tooling
Classifier: Development Status :: 4 - Beta
Classifier: Intended Audience :: Developers
Classifier: License :: OSI Approved :: MIT License
Classifier: Natural Language :: English
Classifier: Operating System :: OS Independent
Classifier: Programming Language :: Python :: 3.7
Classifier: Programming Language :: Python :: 3.8
Classifier: Programming Language :: Python :: 3.9
Classifier: Programming Language :: Python :: 3.10
Classifier: Programming Language :: Python :: 3.11
Requires-Python: >=3.7
Requires-Dist: requests>=2.31.0
Requires-Dist: typing_extensions
Requires-Dist: aiohttp>=3.12.15
Dynamic: author
Dynamic: author-email
Dynamic: classifier
Dynamic: description
Dynamic: description-content-type
Dynamic: home-page
Dynamic: keywords
Dynamic: requires-dist
Dynamic: requires-python
Dynamic: summary
